pytest_expectdir/__init__.py
pytest_expectdir/plugin.py
pytest_expectdir-1.2.0.dist-info/LICENCE
pytest_expectdir-1.2.0.dist-info/METADATA
pytest_expectdir-1.2.0.dist-info/WHEEL
pytest_expectdir-1.2.0.dist-info/entry_points.txt
pytest_expectdir-1.2.0.dist-info/top_level.txt
pytest_expectdir-1.2.0.dist-info/RECORD
