Metadata-Version: 2.1
Name: pytest-expectdir
Version: 1.2.0
Summary: A pytest plugin to provide initial/expected directories, and check a test transforms the initial directory to the expected one
Home-page: https://github.com/hl037/pytest-expectdir
Author: Léo Falventin Hauchecorne
Author-email: hl037.prog@gmail.com
License: MIT
Keywords: pytest test unittest directory file
Classifier: Development Status :: 5 - Production/Stable
Classifier: Intended Audience :: Developers
Classifier: License :: OSI Approved :: MIT License
Classifier: Operating System :: OS Independent
Classifier: Programming Language :: Python :: 3.6
Classifier: Programming Language :: Python :: 3.7
Classifier: Programming Language :: Python :: 3.8
Classifier: Programming Language :: Python :: 3.9
Classifier: Programming Language :: Python :: 3.10
Classifier: Topic :: Software Development :: Quality Assurance
Classifier: Topic :: Software Development :: Testing
Requires-Python: >=3.7
License-File: LICENCE
Requires-Dist: pytest (>=5.0)
